sqlalchemy_bigquery/__init__.py
sqlalchemy_bigquery/_helpers.py
sqlalchemy_bigquery/base.py
sqlalchemy_bigquery/parse_url.py
sqlalchemy_bigquery/requirements.py
sqlalchemy_bigquery/version.py
sqlalchemy_bigquery_user_cred-1.0.0a2.dist-info/AUTHORS
sqlalchemy_bigquery_user_cred-1.0.0a2.dist-info/LICENSE
sqlalchemy_bigquery_user_cred-1.0.0a2.dist-info/METADATA
sqlalchemy_bigquery_user_cred-1.0.0a2.dist-info/WHEEL
sqlalchemy_bigquery_user_cred-1.0.0a2.dist-info/entry_points.txt
sqlalchemy_bigquery_user_cred-1.0.0a2.dist-info/top_level.txt
sqlalchemy_bigquery_user_cred-1.0.0a2.dist-info/RECORD
