Metadata-Version: 2.1
Name: sqlalchemy-bigquery-user-cred
Version: 1.0.0a2
Summary: SQLAlchemy dialect for BigQuery
Home-page: https://github.com/googleapis/python-bigquery-sqlalchemy
Author: The Sqlalchemy-Bigquery Authors
Author-email: googleapis-packages@google.com
License: UNKNOWN
Keywords: bigquery,sqlalchemy
Platform: Posix; MacOS X; Windows
Classifier: Development Status :: 4 - Beta
Classifier: Intended Audience :: Developers
Classifier: License :: OSI Approved :: MIT License
Classifier: Programming Language :: Python
Classifier: Programming Language :: Python :: 3
Classifier: Programming Language :: Python :: 3.6
Classifier: Programming Language :: Python :: 3.7
Classifier: Programming Language :: Python :: 3.8
Classifier: Programming Language :: Python :: 3.9
Classifier: Operating System :: OS Independent
Classifier: Topic :: Database :: Front-Ends
Obsoletes: pybigquery
Requires-Python: >=3.6, <3.10
Requires-Dist: google-api-core (>=1.30.0)
Requires-Dist: google-auth (<3.0.0dev,>=1.25.0)
Requires-Dist: google-cloud-bigquery (>=2.19.0)
Requires-Dist: sqlalchemy (<1.5.0dev,>=1.2.0)
Requires-Dist: future
